setup.py
bin/grade.py
cs1110grade/__init__.py
cs1110grade.egg-info/PKG-INFO
cs1110grade.egg-info/SOURCES.txt
cs1110grade.egg-info/dependency_links.txt
cs1110grade.egg-info/not-zip-safe
cs1110grade.egg-info/top_level.txt
cs1110grade/grade_foo/__init__.py
cs1110grade/grade_foo/__main__.py
cs1110grade/grade_foo/tests.py
cs1110grade/grade_foo/master/__init__.py
cs1110grade/grade_foo/master/foo.py
gradepy/__init__.py
gradepy/command_line.py
gradepy/grade.py