Metadata-Version: 1.0
Name: cs1110grade
Version: 0.1.2
Summary: Tools for automated grading of cs1110 assignments.
Home-page: https://github.com/fredcallaway/grade.py
Author: Fred Callaway
Author-email: fredc@llaway.com
License: MIT
Platform: UNKNOWN
